draftmk/__init__.py
draftmk/__main__.py
draftmk/exceptions.py
draftmk/version.py
draftmk-0.9.2.dist-info/LICENSE
draftmk-0.9.2.dist-info/METADATA
draftmk-0.9.2.dist-info/WHEEL
draftmk-0.9.2.dist-info/entry_points.txt
draftmk-0.9.2.dist-info/RECORD
