Metadata-Version: 2.3
Name: draftmk
Version: 0.9.2
Summary: DraftMk CLI automates setup and preview of MkDocs documentation using Docker, dynamic ports, and Copier templates.
License: MIT
Keywords: mkdocs,documentation,docker,cli,static site,preview server,copier,scaffolding,template,draftmk
Author: Jonatan Mata
Author-email: jonmatum@gmail.com
Requires-Python: >=3.9
Classifier: Programming Language :: Python :: 3.9
Classifier: Programming Language :: Python :: 3.10
Classifier: Programming Language :: Python :: 3.11
Classifier: Programming Language :: Python :: 3.12
Classifier: Programming Language :: Python :: 3.13
Classifier: License :: OSI Approved :: MIT License
Classifier: Operating System :: OS Independent
Requires-Dist: copier (>=9.0.0,<10.0.0)
Requires-Dist: psutil (>=7.0.0,<8.0.0)
Requires-Dist: rich (>=14.0.0,<15.0.0)
